docs/conf.py
tensorclouds/__init__.py
tensorclouds/tensorcloud.py
tensorclouds/utils.py
tensorclouds/data/__init__.py
tensorclouds/data/protein.py
tensorclouds/data/rna.py
tensorclouds/loss/__init__.py
tensorclouds/loss/losses.py
tensorclouds/nn/__init__.py
tensorclouds/nn/denoiser.py
tensorclouds/nn/layer_norm.py
tensorclouds/nn/pooling.py
tensorclouds/nn/profile.py
tensorclouds/nn/radius_graph.py
tensorclouds/nn/residual.py
tensorclouds/nn/self_interaction.py
tensorclouds/nn/spatial_convolution.py
tensorclouds/nn/time_embed.py
tensorclouds/nn/utils.py
tensorclouds/plot/plot_pipe.py
tensorclouds/random/__init__.py
tensorclouds/random/harmonic.py
tensorclouds/random/normal.py
tensorclouds/train/__init__.py
tensorclouds/train/platform.py
tensorclouds/train/registry.py
tensorclouds/train/schedulers.py
tensorclouds/train/trainer.py
tensorclouds/train/utils.py
tensorclouds/transport/__init__.py
tensorclouds/transport/diffusion.py
tensorclouds/transport/flow_matching.py
tensorclouds/transport/mirror_interpolant.py
tensorclouds/transport/one_sided_interpolant.py
tensorclouds/transport/transport.py
tensorclouds/transport/two_sided_interpolant.py
tensorclouds/transport/utils.py
tests/tensorcloud_test.py
tensorclouds-0.1.0.dist-info/METADATA
tensorclouds-0.1.0.dist-info/WHEEL
tensorclouds-0.1.0.dist-info/top_level.txt
tensorclouds-0.1.0.dist-info/RECORD
